{"v":3,"stories":{"components-button--docs":{"id":"components-button--docs","title":"Components/Button","name":"Docs","importPath":"./src/components/atoms/button/Button.stories.tsx","tags":["autodocs","docs"],"storiesImports":[],"kind":"Components/Button","story":"Docs","parameters":{"__id":"components-button--docs","docsOnly":true,"fileName":"./src/components/atoms/button/Button.stories.tsx"}},"components-button--default":{"id":"components-button--default","title":"Components/Button","name":"Default","importPath":"./src/components/atoms/button/Button.stories.tsx","tags":["autodocs","story"],"kind":"Components/Button","story":"Default","parameters":{"__id":"components-button--default","docsOnly":false,"fileName":"./src/components/atoms/button/Button.stories.tsx"}},"components-card--docs":{"id":"components-card--docs","title":"Components/Card","name":"Docs","importPath":"./src/components/atoms/card/Card.stories.tsx","tags":["autodocs","docs"],"storiesImports":[],"kind":"Components/Card","story":"Docs","parameters":{"__id":"components-card--docs","docsOnly":true,"fileName":"./src/components/atoms/card/Card.stories.tsx"}},"components-card--default":{"id":"components-card--default","title":"Components/Card","name":"Default","importPath":"./src/components/atoms/card/Card.stories.tsx","tags":["autodocs","story"],"kind":"Components/Card","story":"Default","parameters":{"__id":"components-card--default","docsOnly":false,"fileName":"./src/components/atoms/card/Card.stories.tsx"}},"components-card--with-children":{"id":"components-card--with-children","title":"Components/Card","name":"With Children","importPath":"./src/components/atoms/card/Card.stories.tsx","tags":["autodocs","story"],"kind":"Components/Card","story":"With Children","parameters":{"__id":"components-card--with-children","docsOnly":false,"fileName":"./src/components/atoms/card/Card.stories.tsx"}},"components-card--with-children-and-image":{"id":"components-card--with-children-and-image","title":"Components/Card","name":"With Children And Image","importPath":"./src/components/atoms/card/Card.stories.tsx","tags":["autodocs","story"],"kind":"Components/Card","story":"With Children And Image","parameters":{"__id":"components-card--with-children-and-image","docsOnly":false,"fileName":"./src/components/atoms/card/Card.stories.tsx"}},"components-card--product-card":{"id":"components-card--product-card","title":"Components/Card","name":"Product Card","importPath":"./src/components/atoms/card/Card.stories.tsx","tags":["autodocs","story"],"kind":"Components/Card","story":"Product Card","parameters":{"__id":"components-card--product-card","docsOnly":false,"fileName":"./src/components/atoms/card/Card.stories.tsx"}},"components-link--docs":{"id":"components-link--docs","title":"Components/Link","name":"Docs","importPath":"./src/components/atoms/link/Link.stories.tsx","tags":["autodocs","docs"],"storiesImports":[],"kind":"Components/Link","story":"Docs","parameters":{"__id":"components-link--docs","docsOnly":true,"fileName":"./src/components/atoms/link/Link.stories.tsx"}},"components-link--default":{"id":"components-link--default","title":"Components/Link","name":"Default","importPath":"./src/components/atoms/link/Link.stories.tsx","tags":["autodocs","story"],"kind":"Components/Link","story":"Default","parameters":{"__id":"components-link--default","docsOnly":false,"fileName":"./src/components/atoms/link/Link.stories.tsx"}},"components-link--external":{"id":"components-link--external","title":"Components/Link","name":"External","importPath":"./src/components/atoms/link/Link.stories.tsx","tags":["autodocs","story"],"kind":"Components/Link","story":"External","parameters":{"__id":"components-link--external","docsOnly":false,"fileName":"./src/components/atoms/link/Link.stories.tsx"}},"guides-card--docs":{"id":"guides-card--docs","title":"Guides/Card","name":"Docs","importPath":"./src/stories/Card.stories.tsx","tags":["autodocs","docs"],"storiesImports":[],"kind":"Guides/Card","story":"Docs","parameters":{"__id":"guides-card--docs","docsOnly":true,"fileName":"./src/stories/Card.stories.tsx"}},"guides-card--default":{"id":"guides-card--default","title":"Guides/Card","name":"Default","importPath":"./src/stories/Card.stories.tsx","tags":["autodocs","story"],"kind":"Guides/Card","story":"Default","parameters":{"__id":"guides-card--default","docsOnly":false,"fileName":"./src/stories/Card.stories.tsx"}},"guides-card--seo":{"id":"guides-card--seo","title":"Guides/Card","name":"SEO","importPath":"./src/stories/Card.stories.tsx","tags":["autodocs","story"],"kind":"Guides/Card","story":"SEO","parameters":{"__id":"guides-card--seo","docsOnly":false,"fileName":"./src/stories/Card.stories.tsx"}}}}
